carcara/__init__.py
carcara/_version.py
carcara/atoms_dataset.py
carcara/graph_converter.py
carcara/io.py
carcara/ase_interface/calculator.py
carcara/explain/subgraphx.py
carcara-25.12.0.dist-info/METADATA
carcara-25.12.0.dist-info/WHEEL
carcara-25.12.0.dist-info/licenses/LICENSE
carcara-25.12.0.dist-info/RECORD
