Metadata-Version: 2.4
Name: carcara
Version: 25.12.0
Summary: Machine learning for atomistic simulations.
Project-URL: Homepage, https://github.com/seixasgroup/carcara
Project-URL: Bug Tracker, https://github.com/seixasgroup/carcara/issues
Author-email: Leandro Seixas <leandro.seixas@proton.me>
License: MIT License
License-File: LICENSE
Classifier: License :: OSI Approved :: MIT License
Classifier: Operating System :: OS Independent
Classifier: Programming Language :: Python :: 3
Classifier: Topic :: Scientific/Engineering :: Chemistry
Classifier: Topic :: Scientific/Engineering :: Physics
Requires-Python: >=3.10
Requires-Dist: ase
Requires-Dist: matplotlib
Requires-Dist: ml-dtypes
Requires-Dist: networkx
Requires-Dist: numpy>=2.0.0
Requires-Dist: pandas
Requires-Dist: pytest
Requires-Dist: pyyaml
Requires-Dist: scipy
Requires-Dist: torch
Requires-Dist: torch-geometric
